minplascalc/__init__.py
minplascalc/functions_radiation.py
minplascalc/functions_transport.py
minplascalc/mixture.py
minplascalc/parsers.py
minplascalc/species.py
minplascalc/units.py
minplascalc/utils.py
minplascalc/data/demo/nist/nist_Oplus_emission_lines
minplascalc/data/demo/nist/nist_Oplus_levels
minplascalc/data/species/C++.json
minplascalc/data/species/C+.json
minplascalc/data/species/C.json
minplascalc/data/species/CO+.json
minplascalc/data/species/CO.json
minplascalc/data/species/O++.json
minplascalc/data/species/O+.json
minplascalc/data/species/O-.json
minplascalc/data/species/O.json
minplascalc/data/species/O2+.json
minplascalc/data/species/O2-.json
minplascalc/data/species/O2.json
minplascalc/data/species/Si++.json
minplascalc/data/species/Si+.json
minplascalc/data/species/Si.json
minplascalc/data/species/SiO+.json
minplascalc/data/species/SiO.json
minplascalc-1.0.2.dist-info/METADATA
minplascalc-1.0.2.dist-info/WHEEL
minplascalc-1.0.2.dist-info/licenses/LICENSE
minplascalc-1.0.2.dist-info/RECORD
