Metadata-Version: 2.4
Name: minplascalc
Version: 1.0.2
Summary: A simple set of tools for doing calculations of thermal plasma compositions relevant to metallurgical problems using Python 3
Project-URL: Homepage, https://github.com/quinnreynolds/minplascalc
Author-email: Quinn Reynolds <quinnr@mintek.co.za>
License: GPLv3
License-File: LICENSE
Keywords: composition,gibbs,plasma
Classifier: Development Status :: 3 - Alpha
Classifier: Intended Audience :: Science/Research
Classifier: License :: OSI Approved :: GNU General Public License v3 (GPLv3)
Classifier: Programming Language :: Python :: 3.11
Classifier: Programming Language :: Python :: 3.12
Classifier: Programming Language :: Python :: 3.13
Classifier: Topic :: Scientific/Engineering :: Chemistry
Classifier: Topic :: Scientific/Engineering :: Physics
Requires-Python: >=3.11
Requires-Dist: numba
Requires-Dist: numpy
Requires-Dist: scipy
